{
  "users": [
    {
      "firstName": "Homer",
      "lastName": "Simpson",
      "email": "homer@simpson.com",
      "password": "secret",
      "_id": "6f98f550-f979-4b69-a9aa-b8690923a9cc"
    },
    {
      "firstName": "Marge",
      "lastName": "Simpson",
      "email": "marge@simpson.com",
      "password": "secret",
      "_id": "a6dd9fb5-edb4-437c-9934-c60b75cb7781"
    },
    {
      "firstName": "Bart",
      "lastName": "Simpson",
      "email": "bart@simpson.com",
      "password": "secret",
      "_id": "a447f03f-c1e5-4ad3-b023-e2716b6e3320"
    }
  ],
  "playlists": [],
  "tracks": []
}